nda_api/__init__.py
nda_api/convert_nda_std.py
nda_api/html_to_df.py
nda_api/nda_api.py
nda_api-0.0.3.dist-info/METADATA
nda_api-0.0.3.dist-info/WHEEL
nda_api-0.0.3.dist-info/top_level.txt
nda_api-0.0.3.dist-info/RECORD
