Metadata-Version: 2.1
Name: nda-api
Version: 0.0.3
Summary: Package to fetch data from Nordea
Home-page: https://github.com/olundberg/nda_api
Author: Oscar Lundberg
Author-email: lundberg.oscar@gmail.com
License: UNKNOWN
Download-URL: https://github.com/olundberg/nda_api/archive/refs/tags/v_0.0.3.tar.gz
Platform: UNKNOWN
Classifier: Programming Language :: Python :: 3
Classifier: License :: OSI Approved :: MIT License
Classifier: Operating System :: OS Independent
Requires-Python: >=3.9
Requires-Dist: webdriver-manager
Requires-Dist: selenium (>=3.141.0)
Requires-Dist: pandas
Requires-Dist: lxml
Requires-Dist: html5lib
Requires-Dist: bs4
